nmc_met_io/DataBlock_pb2.py
nmc_met_io/__init__.py
nmc_met_io/config.py
nmc_met_io/export_micaps.py
nmc_met_io/export_radar.py
nmc_met_io/read_a.py
nmc_met_io/read_grads.py
nmc_met_io/read_grib.py
nmc_met_io/read_j.py
nmc_met_io/read_micaps.py
nmc_met_io/read_radar.py
nmc_met_io/read_satellite.py
nmc_met_io/retrieve_aws_server.py
nmc_met_io/retrieve_caiy_api.py
nmc_met_io/retrieve_cassandraDB.py
nmc_met_io/retrieve_cimiss_history.py
nmc_met_io/retrieve_cimiss_server.py
nmc_met_io/retrieve_cma_weather.py
nmc_met_io/retrieve_cmadaas.py
nmc_met_io/retrieve_cmadaas_history.py
nmc_met_io/retrieve_cmadass_history.py
nmc_met_io/retrieve_cmadass_rise.py
nmc_met_io/retrieve_ghcn.py
nmc_met_io/retrieve_history.py
nmc_met_io/retrieve_micaps_server.py
nmc_met_io/util.py
nmc_met_io/utility.py
nmc_met_io-0.1.16.0.dist-info/licenses/LICENSE
nmc_met_io-0.1.16.0.dist-info/METADATA
nmc_met_io-0.1.16.0.dist-info/WHEEL
nmc_met_io-0.1.16.0.dist-info/top_level.txt
nmc_met_io-0.1.16.0.dist-info/RECORD
