Metadata-Version: 2.4
Name: nmc_met_io
Version: 0.1.16.0
Summary: Collection of tools for I/O or accessing meteorological data.
Home-page: https://github.com/nmcdev/nmc_met_io
Author: The R & D Center for Weather Forecasting Technology in NMC, CMA
Author-email: kan.dai@foxmail.com
License: GPL3
Platform: all
Classifier: Development Status :: 4 - Beta
Classifier: Intended Audience :: Developers
Classifier: Intended Audience :: Science/Research
Classifier: License :: OSI Approved :: GNU General Public License v3 (GPLv3)
Classifier: Topic :: Scientific/Engineering
Classifier: Topic :: Scientific/Engineering :: Atmospheric Science
Classifier: Programming Language :: Python :: 3.9
Classifier: Programming Language :: Python :: 3.10
Classifier: Programming Language :: Python :: 3.11
Classifier: Programming Language :: Python :: 3.12
Classifier: Operating System :: POSIX :: Linux
Classifier: Operating System :: MacOS :: MacOS X
Classifier: Operating System :: Microsoft :: Windows
Requires-Python: >=3.9
License-File: LICENSE
Requires-Dist: numpy>=1.24.0
Requires-Dist: scipy>=1.10.0
Requires-Dist: pandas>=2.0.0
Requires-Dist: xarray>=2023.0.0
Requires-Dist: protobuf>=4.21.0
Requires-Dist: urllib3>=1.26.0
Requires-Dist: tqdm>=4.65.0
Requires-Dist: python-dateutil>=2.8.2
Requires-Dist: openpyxl>=3.1.0
Dynamic: author
Dynamic: author-email
Dynamic: classifier
Dynamic: description
Dynamic: description-content-type
Dynamic: home-page
Dynamic: license
Dynamic: license-file
Dynamic: platform
Dynamic: requires-dist
Dynamic: requires-python
Dynamic: summary
